MANIFEST.in
setup.py
django_softhyphen.egg-info/PKG-INFO
django_softhyphen.egg-info/SOURCES.txt
django_softhyphen.egg-info/dependency_links.txt
django_softhyphen.egg-info/requires.txt
django_softhyphen.egg-info/top_level.txt
softhyphen/__init__.py
softhyphen/html.py
softhyphen/hyphenator.py
softhyphen/models.py
softhyphen/tests.py
softhyphen/dicts/COPYING.GPL
softhyphen/dicts/OLVASSEL_hyph_hu_HU.txt
softhyphen/dicts/README
softhyphen/dicts/README-COMO-HYPH_ES.txt
softhyphen/dicts/README.md
softhyphen/dicts/README_hyph_cs_CZ.txt
softhyphen/dicts/README_hyph_da_DK.txt
softhyphen/dicts/README_hyph_de_CH.txt
softhyphen/dicts/README_hyph_de_DE.txt
softhyphen/dicts/README_hyph_el_GR.txt
softhyphen/dicts/README_hyph_en_CA.txt
softhyphen/dicts/README_hyph_en_GB.txt
softhyphen/dicts/README_hyph_en_US.txt
softhyphen/dicts/README_hyph_es_ES.txt
softhyphen/dicts/README_hyph_fi_FI.txt
softhyphen/dicts/README_hyph_ga_IE.txt
softhyphen/dicts/README_hyph_hu_HU.txt
softhyphen/dicts/README_hyph_ia.txt
softhyphen/dicts/README_hyph_is_IS.txt
softhyphen/dicts/README_hyph_it_IT.txt
softhyphen/dicts/README_hyph_lt_LT.txt
softhyphen/dicts/README_hyph_nl_NL.txt
softhyphen/dicts/README_hyph_pl_PL.txt
softhyphen/dicts/README_hyph_pt_BR.txt
softhyphen/dicts/README_hyph_pt_PT.txt
softhyphen/dicts/README_hyph_ru_RU.txt
softhyphen/dicts/README_hyph_sk_SK.txt
softhyphen/dicts/README_hyph_sl_SI.txt
softhyphen/dicts/README_hyph_sv_SE.txt
softhyphen/dicts/README_hyph_uk_UA.txt
softhyphen/dicts/README_id_ID.txt
softhyphen/dicts/README_sh.txt
softhyphen/dicts/README_sr.txt
softhyphen/dicts/hyph_cs_CZ.dic
softhyphen/dicts/hyph_da_DK.dic
softhyphen/dicts/hyph_de_CH.dic
softhyphen/dicts/hyph_de_DE.dic
softhyphen/dicts/hyph_el_GR.dic
softhyphen/dicts/hyph_en_CA.dic
softhyphen/dicts/hyph_en_GB.dic
softhyphen/dicts/hyph_en_US.dic
softhyphen/dicts/hyph_es_ES.dic
softhyphen/dicts/hyph_fi_FI.dic
softhyphen/dicts/hyph_ga_IE.dic
softhyphen/dicts/hyph_hu_HU.dic
softhyphen/dicts/hyph_hu_HU_nonutf.dic
softhyphen/dicts/hyph_ia.dic
softhyphen/dicts/hyph_id_ID.dic
softhyphen/dicts/hyph_is_IS.dic
softhyphen/dicts/hyph_it_IT.dic
softhyphen/dicts/hyph_lt_LT.dic
softhyphen/dicts/hyph_nl_NL.dic
