Metadata-Version: 1.1
Name: django-softhyphen
Version: 1.1.0
Summary: A Python library for hyphenating HTML in your Django project
Home-page: https://github.com/datadesk/django-softhyphen/
Author: Ben Welsh
Author-email: ben.welsh@gmail.com
License: UNKNOWN
Platform: UNKNOWN
Classifier: Programming Language :: Python
Classifier: Programming Language :: Python :: 2.7
Classifier: Programming Language :: Python :: 3.4
Classifier: Programming Language :: Python :: 3.5
